{
    "boundary_coords": 
    [
        [-1.0, -2.9], 
        [13.0, -2.9], 
        [13.0, 13.0], 
        [-1.0, 13.0]
    ], 
    "obstacle_list": 
    [
        [[5.0, 5.0], [5.0, 7.0], [7.0, 7.0], [7.0, 5.0]],
        [[1.0, 5.0], [1.0, 7.0], [3.0, 7.0], [3.0, 5.0]],
        [[9.0, 5.0], [9.0, 7.0], [11.0, 7.0], [11.0, 5.0]],
        [[5.0, 9.0], [5.0, 11.0], [7.0, 11.0], [7.0, 9.0]],
        [[1.0, 9.0], [1.0, 11.0], [3.0, 11.0], [3.0, 9.0]],
        [[9.0, 9.0], [9.0, 11.0], [11.0, 11.0], [11.0, 9.0]],
        [[5.0, 1.0], [5.0, 3.0], [7.0, 3.0], [7.0, 1.0]],
        [[1.0, 1.0], [1.0, 3.0], [3.0, 3.0], [3.0, 1.0]],
        [[9.0, 1.0], [9.0, 3.0], [11.0, 3.0], [11.0, 1.0]]

    ],
    "obstacle_dict":
    [
        {"id_": 1, "name": "obstacle_21", "vertices": [[5.0, 5.0], [5.0, 7.0], [7.0, 7.0], [7.0, 5.0]]},
        {"id_": 2, "name": "obstacle_22", "vertices": [[1.0, 5.0], [1.0, 7.0], [3.0, 7.0], [3.0, 5.0]]},
        {"id_": 3, "name": "obstacle_23", "vertices": [[9.0, 5.0], [9.0, 7.0], [11.0, 7.0], [11.0, 5.0]]},
        {"id_": 4, "name": "obstacle_31", "vertices": [[5.0, 9.0], [5.0, 11.0], [7.0, 11.0], [7.0, 9.0]]},
        {"id_": 5, "name": "obstacle_32", "vertices": [[1.0, 9.0], [1.0, 11.0], [3.0, 11.0], [3.0, 9.0]]},
        {"id_": 6, "name": "obstacle_33", "vertices": [[9.0, 9.0], [9.0, 11.0], [11.0, 11.0], [11.0, 9.0]]},
        {"id_": 7, "name": "obstacle_11", "vertices": [[5.0, 1.0], [5.0, 3.0], [7.0, 3.0], [7.0, 1.0]]},
        {"id_": 8, "name": "obstacle_12", "vertices": [[1.0, 1.0], [1.0, 3.0], [3.0, 3.0], [3.0, 1.0]]},
        {"id_": 9, "name": "obstacle_13", "vertices": [[9.0, 1.0], [9.0, 3.0], [11.0, 3.0], [11.0, 1.0]]}
    ]
}